mcqa/__init__.py
mcqa-0.0.1.dist-info/LICENSE
mcqa-0.0.1.dist-info/METADATA
mcqa-0.0.1.dist-info/WHEEL
mcqa-0.0.1.dist-info/top_level.txt
mcqa-0.0.1.dist-info/RECORD
